README.rst
setup.py
jupydbg/__init__.py
jupydbg/catch.py
jupydbg/errdisp.py
jupydbg/ezdebug.py
jupydbg/jupytest.py
jupydbg.egg-info/PKG-INFO
jupydbg.egg-info/SOURCES.txt
jupydbg.egg-info/dependency_links.txt
jupydbg.egg-info/requires.txt
jupydbg.egg-info/top_level.txt