Metadata-Version: 1.1
Name: jupydbg
Version: 0.1.1
Summary: Cell magic to inspect the stack after an error + Interactive unittest player
Home-page: http://github.com/gcoffin/jupydbg
Author: Guillaume Coffin
Author-email: guill.coffin@gmail.com
License: GPLv3
Download-URL: https://github.com/gcoffin/jupydbg/archive/0.1.tar.gz
Keywords: interactive unittest debug stack
Platform: UNKNOWN
Classifier: Development Status :: 3 - Alpha
Classifier: Intended Audience :: Developers
Classifier: License :: OSI Approved :: GNU General Public License v3 (GPLv3)
Classifier: Programming Language :: Python :: 2.7
Classifier: Programming Language :: Python :: 3
Classifier: Operating System :: MacOS :: MacOS X
Classifier: Operating System :: Microsoft :: Windows
Classifier: Operating System :: POSIX
